Workbook

Sheet How it works
A1: How this ledger works
A2: Read this once. Then you only ever type on the Daily tab.
B4: THE SIX LANES — every lead is one of these
B5: Lead came from | C5: Sold to | D5: Who paid for the lead | E5: Who collects the sale | F5: Effect between Bob and Olivia
B6: Bob's own campaign | C6: Olivia | D6: Bob (his ad spend) | E6: Olivia buys it | F6: OLIVIA OWES BOB — price per lead
B7: S | C7: Olivia | D7: Bob (pays S) | E7: Olivia buys it | F7: OLIVIA OWES BOB — same price per lead
B8: GS | C8: Olivia | D8: Olivia (pays GS) | E8: Olivia's own buyer | F8: nothing — both sides are Olivia's
B9: Bob's own campaign | C9: Bob's private buyer (GLU) | D9: Bob (his ad spend) | E9: Bob (from GLU) | F9: nothing — both sides are Bob's *
B10: S | C10: Bob's private buyer (GLU) | D10: Bob (pays S) | E10: Bob (from GLU) | F10: nothing — both sides are Bob's *
B11: GS | C11: Bob's private buyer (GLU) | D11: Olivia (pays GS) | E11: Bob (from GLU) | F11: BOB OWES OLIVIA — transfer price per lead
B13: * plus a per-lead panel fee, if you agree one. The rate is 0 by default, so it does nothing until you put a number in it.
B16: THE ONE RULE
B17: NET = (what Olivia owes Bob) - (what Bob owes Olivia) +/- the other cost, if you settle it
B19: The NET is always written from Olivia's side. Positive means Olivia pays Bob. Negative means Bob pays Olivia. It is the last column on the Daily tab.
B22: WHAT TO DO EACH DAY
B23: 1. Open the Daily tab. Put the date in column A.
B24: 2. Put the six lead counts in columns B to G. Leave a lane blank if it did not happen.
B25: 3. The three price columns fill themselves from the Rates tab. Type over one only if the price changed that day.
B26: 4. If there was any other cost, put the amount, who paid it, and YES or NO in columns N, O, P.
B27: 5. Read the last column. It tells you who pays whom, and how much.
B30: COLOUR CODE
B31: Yellow cells — you type in these
... B40: d. All of Bob's private buyers are counted together. Only GLU is named so far.

Sheet Rates
A1: Rates — set these once
A2: The Daily tab reads the three settlement rates from here.
B4: SETTLEMENT RATES — these three are the only ones that move money between Bob and Olivia
B5: Rate | C5: Value | D5: Direction | E5: Notes
B6: Bob to Olivia — price per lead | C6: 8 | D6: Olivia pays Bob | E6: Same price whether the lead came from Bob's campaign or from S.
B7: GS lead sold to Bob's private buyer — price per lead | C7: =C15 | D7: Bob pays Olivia | E7: Defaults to what GS costs Olivia. Type a number over it if you agreed a different price.
B8: Panel fee per lead on Bob's private-buyer leads | C8: 0 | D8: Bob pays Olivia | E8: Leave at 0 if Bob pays nothing for using Olivia's panel.
B11: REFERENCE ONLY — recorded so the prices are written down. Nothing here changes what Bob and Olivia owe each other.
B12: Rate | C12: Value | D12: Who pays it | E12: Notes
B13: Bob's own campaign — cost per lead | C13: 0 | D13: Bob | E13: Bob's ad spend divided by leads.
B14: S — cost per lead | C14: 0 | D14: Bob | E14: What Bob pays S.
B15: GS — cost per lead | C15: 6 | D15: Olivia | E15: What Olivia pays GS. Row 7 above defaults to this.
B16: Bob to GLU — price per lead | C16: 0 | D16: GLU pays Bob | E16: Bob's private-buyer price.
B19: Currency | C19: USD | E19: Label only. Every amount in the file is in this currency.

Sheet Daily
A1: Daily ledger — type the date and the six lead counts, read the last column
A2: Date | B2: Leads Bob's own -> Olivia | C2: Leads S -> Olivia | D2: Leads GS -> Olivia | E2: Leads Bob's own -> GLU | F2: Leads S -> GLU | G2: Leads GS -> GLU | H2: Total leads | I2: Price Bob -> Olivia per lead | J2: Price GS -> GLU per lead | K2: Panel fee per lead | L2: OLIVIA OWES BOB | M2: BOB OWES OLIVIA | N2: Other cost amount | O2: Other cost paid by | P2: Settle it? YES / NO | Q2: Other cost adjustment | R2: Who pays whom | S2: NET (+ Olivia pays Bob) (- Bob pays Olivia)
H3: =IF($A3="","",SUM($B3:$G3)) | I3: =IF($A3="","",Rates!$C$6) | J3: =IF($A3="","",Rates!$C$7) | K3: =IF($A3="","",Rates!$C$8) | L3: =IF($A3="","",($B3+$C3)*$I3) | M3: =IF($A3="","",$G3*$J3+($E3+$F3+$G3)*$K3) | Q3: =IF($A3="","",IF($P3="YES",IF($O3="Bob",$N3,-$N3),0)) | R3: =IF($A3="","",IF(ROUND($S3,2)>0,"Olivia pays Bob "&TEXT($S3,"#,##0.00"),IF(ROUND($S3,2)<0,"Bob pays Olivia "&TEXT(-$S3,"#,##0.00"),"Nothing owed"))) | S3: =IF($A3="","",$L3-$M3+$Q3)
H4: =IF($A4="","",SUM($B4:$G4)) | I4: =IF($A4="","",Rates!$C$6) | J4: =IF($A4="","",Rates!$C$7) | K4: =IF($A4="","",Rates!$C$8) | L4: =IF($A4="","",($B4+$C4)*$I4) | M4: =IF($A4="","",$G4*$J4+($E4+$F4+$G4)*$K4) | Q4: =IF($A4="","",IF($P4="YES",IF($O4="Bob",$N4,-$N4),0)) | R4: =IF($A4="","",IF(ROUND($S4,2)>0,"Olivia pays Bob "&TEXT($S4,"#,##0.00"),IF(ROUND($S4,2)<0,"Bob pays Olivia "&TEXT(-$S4,"#,##0.00"),"Nothing owed"))) | S4: =IF($A4="","",$L4-$M4+$Q4)
H5: =IF($A5="","",SUM($B5:$G5)) | I5: =IF($A5="","",Rates!$C$6) | J5: =IF($A5="","",Rates!$C$7) | K5: =IF($A5="","",Rates!$C$8) | L5: =IF($A5="","",($B5+$C5)*$I5) | M5: =IF($A5="","",$G5*$J5+($E5+$F5+$G5)*$K5) | Q5: =IF($A5="","",IF($P5="YES",IF($O5="Bob",$N5,-$N5),0)) | R5: =IF($A5="","",IF(ROUND($S5,2)>0,"Olivia pays Bob "&TEXT($S5,"#,##0.00"),IF(ROUND($S5,2)<0,"Bob pays Olivia "&TEXT(-$S5,"#,##0.00"),"Nothing owed"))) | S5: =IF($A5="","",$L5-$M5+$Q5)
H6: =IF($A6="","",SUM($B6:$G6)) | I6: =IF($A6="","",Rates!$C$6) | J6: =IF($A6="","",Rates!$C$7) | K6: =IF($A6="","",Rates!$C$8) | L6: =IF($A6="","",($B6+$C6)*$I6) | M6: =IF($A6="","",$G6*$J6+($E6+$F6+$G6)*$K6) | Q6: =IF($A6="","",IF($P6="YES",IF($O6="Bob",$N6,-$N6),0)) | R6: =IF($A6="","",IF(ROUND($S6,2)>0,"Olivia pays Bob "&TEXT($S6,"#,##0.00"),IF(ROUND($S6,2)<0,"Bob pays Olivia "&TEXT(-$S6,"#,##0.00"),"Nothing owed"))) | S6: =IF($A6="","",$L6-$M6+$Q6)
H7: =IF($A7="","",SUM($B7:$G7)) | I7: =IF($A7="","",Rates!$C$6) | J7: =IF($A7="","",Rates!$C$7) | K7: =IF($A7="","",Rates!$C$8) | L7: =IF($A7="","",($B7+$C7)*$I7) | M7: =IF($A7="","",$G7*$J7+($E7+$F7+$G7)*$K7) | Q7: =IF($A7="","",IF($P7="YES",IF($O7="Bob",$N7,-$N7),0)) | R7: =IF($A7="","",IF(ROUND($S7,2)>0,"Olivia pays Bob "&TEXT($S7,"#,##0.00"),IF(ROUND($S7,2)<0,"Bob pays Olivia "&TEXT(-$S7,"#,##0.00"),"Nothing owed"))) | S7: =IF($A7="","",$L7-$M7+$Q7)
H8: =IF($A8="","",SUM($B8:$G8)) | I8: =IF($A8="","",Rates!$C$6) | J8: =IF($A8="","",Rates!$C$7) | K8: =IF($A8="","",Rates!$C$8) | L8: =IF($A8="","",($B8+$C8)*$I8) | M8: =IF($A8="","",$G8*$J8+($E8+$F8+$G8)*$K8) | Q8: =IF($A8="","",IF($P8="YES",IF($O8="Bob",$N8,-$N8),0)) | R8: =IF($A8="","",IF(ROUND($S8,2)>0,"Olivia pays Bob "&TEXT($S8,"#,##0.00"),IF(ROUND($S8,2)<0,"Bob pays Olivia "&TEXT(-$S8,"#,##0.00"),"Nothing owed"))) | S8: =IF($A8="","",$L8-$M8+$Q8)
H9: =IF($A9="","",SUM($B9:$G9)) | I9: =IF($A9="","",Rates!$C$6) | J9: =IF($A9="","",Rates!$C$7) | K9: =IF($A9="","",Rates!$C$8) | L9: =IF($A9="","",($B9+$C9)*$I9) | M9: =IF($A9="","",$G9*$J9+($E9+$F9+$G9)*$K9) | Q9: =IF($A9="","",IF($P9="YES",IF($O9="Bob",$N9,-$N9),0)) | R9: =IF($A9="","",IF(ROUND($S9,2)>0,"Olivia pays Bob "&TEXT($S9,"#,##0.00"),IF(ROUND($S9,2)<0,"Bob pays Olivia "&TEXT(-$S9,"#,##0.00"),"Nothing owed"))) | S9: =IF($A9="","",$L9-$M9+$Q9)
H10: =IF($A10="","",SUM($B10:$G10)) | I10: =IF($A10="","",Rates!$C$6) | J10: =IF($A10="","",Rates!$C$7) | K10: =IF($A10="","",Rates!$C$8) | L10: =IF($A10="","",($B10+$C10)*$I10) | M10: =IF($A10="","",$G10*$J10+($E10+$F10+$G10)*$K10) | Q10: =IF($A10="","",IF($P10="YES",IF($O10="Bob",$N10,-$N10),0)) | R10: =IF($A10="","",IF(ROUND($S10,2)>0,"Olivia pays Bob "&TEXT($S10,"#,##0.00"),IF(ROUND($S10,2)<0,"Bob pays Olivia "&TEXT(-$S10,"#,##0.00"),"Nothing owed"))) | S10: =IF($A10="","",$L10-$M10+$Q10)
H11: =IF($A11="","",SUM($B11:$G11)) | I11: =IF($A11="","",Rates!$C$6) | J11: =IF($A11="","",Rates!$C$7) | K11: =IF($A11="","",Rates!$C$8) | L11: =IF($A11="","",($B11+$C11)*$I11) | M11: =IF($A11="","",$G11*$J11+($E11+$F11+$G11)*$K11) | Q11: =IF($A11="","",IF($P11="YES",IF($O11="Bob",$N11,-$N11),0)) | R11: =IF($A11="","",IF(ROUND($S11,2)>0,"Olivia pays Bob "&TEXT($S11,"#,##0.00"),IF(ROUND($S11,2)<0,"Bob pays Olivia "&TEXT(-$S11,"#,##0.00"),"Nothing owed"))) | S11: =IF($A11="","",$L11-$M11+$Q11)
H12: =IF($A12="","",SUM($B12:$G12)) | I12: =IF($A12="","",Rates!$C$6) | J12: =IF($A12="","",Rates!$C$7) | K12: =IF($A12="","",Rates!$C$8) | L12: =IF($A12="","",($B12+$C12)*$I12) | M12: =IF($A12="","",$G12*$J12+($E12+$F12+$G12)*$K12) | Q12: =IF($A12="","",IF($P12="YES",IF($O12="Bob",$N12,-$N12),0)) | R12: =IF($A12="","",IF(ROUND($S12,2)>0,"Olivia pays Bob "&TEXT($S12,"#,##0.00"),IF(ROUND($S12,2)<0,"Bob pays Olivia "&TEXT(-$S12,"#,##0.00"),"Nothing owed"))) | S12: =IF($A12="","",$L12-$M12+$Q12)
H13: =IF($A13="","",SUM($B13:$G13)) | I13: =IF($A13="","",Rates!$C$6) | J13: =IF($A13="","",Rates!$C$7) | K13: =IF($A13="","",Rates!$C$8) | L13: =IF($A13="","",($B13+$C13)*$I13) | M13: =IF($A13="","",$G13*$J13+($E13+$F13+$G13)*$K13) | Q13: =IF($A13="","",IF($P13="YES",IF($O13="Bob",$N13,-$N13),0)) | R13: =IF($A13="","",IF(ROUND($S13,2)>0,"Olivia pays Bob "&TEXT($S13,"#,##0.00"),IF(ROUND($S13,2)<0,"Bob pays Olivia "&TEXT(-$S13,"#,##0.00"),"Nothing owed"))) | S13: =IF($A13="","",$L13-$M13+$Q13)
H14: =IF($A14="","",SUM($B14:$G14)) | I14: =IF($A14="","",Rates!$C$6) | J14: =IF($A14="","",Rates!$C$7) | K14: =IF($A14="","",Rates!$C$8) | L14: =IF($A14="","",($B14+$C14)*$I14) | M14: =IF($A14="","",$G14*$J14+($E14+$F14+$G14)*$K14) | Q14: =IF($A14="","",IF($P14="YES",IF($O14="Bob",$N14,-$N14),0)) | R14: =IF($A14="","",IF(ROUND($S14,2)>0,"Olivia pays Bob "&TEXT($S14,"#,##0.00"),IF(ROUND($S14,2)<0,"Bob pays Olivia "&TEXT(-$S14,"#,##0.00"),"Nothing owed"))) | S14: =IF($A14="","",$L14-$M14+$Q14)
... H302: =IF($A302="","",SUM($B302:$G302)) | I302: =IF($A302="","",Rates!$C$6) | J302: =IF($A302="","",Rates!$C$7) | K302: =IF($A302="","",Rates!$C$8) | L302: =IF($A302="","",($B302+$C302)*$I302) | M302: =IF($A302="","",$G302*$J302+($E302+$F302+$G302)*$K302) | Q302: =IF($A302="","",IF($P302="YES",IF($O302="Bob",$N302,-$N302),0)) | R302: =IF($A302="","",IF(ROUND($S302,2)>0,"Olivia pays Bob "&TEXT($S302,"#,##0.00"),IF(ROUND($S302,2)<0,"Bob pays Olivia "&TEXT(-$S302,"#,##0.00"),"Nothing owed"))) | S302: =IF($A302="","",$L302-$M302+$Q302)

Sheet Summary
A1: Summary — the balance between Bob and Olivia
A2: Change the two dates to settle a week, a month, or everything.
B4: From date | C4: 36526
B5: To date | C5: 73050
B7: LEADS IN THE PERIOD
B8: Lane | C8: Leads
B9: Bob's own campaign -> Olivia | C9: =SUMIFS(Daily!$B$3:$B$302,Daily!$A$3:$A$302,">="&$C$4,Daily!$A$3:$A$302,"<="&$C$5)
B10: S -> Olivia | C10: =SUMIFS(Daily!$C$3:$C$302,Daily!$A$3:$A$302,">="&$C$4,Daily!$A$3:$A$302,"<="&$C$5)
B11: GS -> Olivia | C11: =SUMIFS(Daily!$D$3:$D$302,Daily!$A$3:$A$302,">="&$C$4,Daily!$A$3:$A$302,"<="&$C$5)
B12: Bob's own campaign -> Bob's private buyer | C12: =SUMIFS(Daily!$E$3:$E$302,Daily!$A$3:$A$302,">="&$C$4,Daily!$A$3:$A$302,"<="&$C$5)
B13: S -> Bob's private buyer | C13: =SUMIFS(Daily!$F$3:$F$302,Daily!$A$3:$A$302,">="&$C$4,Daily!$A$3:$A$302,"<="&$C$5)
B14: GS -> Bob's private buyer | C14: =SUMIFS(Daily!$G$3:$G$302,Daily!$A$3:$A$302,">="&$C$4,Daily!$A$3:$A$302,"<="&$C$5)
B15: Total leads | C15: =SUM(C9:C14)
B17: MONEY IN THE PERIOD
B18: Olivia owes Bob — lead sales | C18: =SUMIFS(Daily!$L$3:$L$302,Daily!$A$3:$A$302,">="&$C$4,Daily!$A$3:$A$302,"<="&$C$5) | E18: Every lead Bob sold her, from his own campaign or from S.
B19: Bob owes Olivia — GS leads to his buyers, and panel fee | C19: =SUMIFS(Daily!$M$3:$M$302,Daily!$A$3:$A$302,">="&$C$4,Daily!$A$3:$A$302,"<="&$C$5) | E19: GS leads Olivia paid for that went to Bob's private buyer.
B20: Other cost adjustment | C20: =SUMIFS(Daily!$Q$3:$Q$302,Daily!$A$3:$A$302,">="&$C$4,Daily!$A$3:$A$302,"<="&$C$5) | E20: Plus if Bob paid it, minus if Olivia paid it. Only the rows marked YES.
B21: NET FOR THE PERIOD | C21: =C18-C19+C20
B23: CHECKS — all four must read 0 | E23: Each one rebuilds a figure a different way. A number other than 0 means a formula has been typed over.
B24: 1. Lead money, rebuilt from the counts and the prices | C24: =ROUND(SUMPRODUCT((Daily!$A$3:$A$302>=$C$4)*(Daily!$A$3:$A$302<=$C$5)*(Daily!$B$3:$B$302+Daily!$C$3:$C$302),Daily!$I$3:$I$302)-SUMPRODUCT((Daily!$A$3:$A$302>=$C$4)*(Daily!$A$3:$A$302<=$C$5)*Daily!$G$3:$G$302,Daily!$J$3:$J$302)-SUMPRODUCT((Daily!$A$3:$A$302>=$C$4)*(Daily!$A$3:$A$302<=$C$5)*(Daily!$E$3:$E$302+Daily!$F$3:$F$302+Daily!$G$3:$G$302),Daily!$K$3:$K$302)-(C18-C19),6) | E24: Multiplies the lead counts by the prices itself, instead of trusting the two money columns.
B25: 2. Other cost, rebuilt from the amount, payer and YES/NO | C25: =ROUND(SUMIFS(Daily!$N$3:$N$302,Daily!$P$3:$P$302,"YES",Daily!$O$3:$O$302,"Bob",Daily!$A$3:$A$302,">="&$C$4,Daily!$A$3:$A$302,"<="&$C$5)-SUMIFS(Daily!$N$3:$N$302,Daily!$P$3:$P$302,"YES",Daily!$O$3:$O$302,"Olivia",Daily!$A$3:$A$302,">="&$C$4,Daily!$A$3:$A$302,"<="&$C$5)-C20,6) | E25: Re-reads the three other-cost columns instead of trusting the adjustment column.
B26: 3. The daily NET column adds up to the same net | C26: =ROUND(C18-C19+C20-SUMIFS(Daily!$S$3:$S$302,Daily!$A$3:$A$302,">="&$C$4,Daily!$A$3:$A$302,"<="&$C$5),6) | E26: Catches a NET cell that has had a number typed straight into it.
B27: 4. Days in the period with no price on them | C27: =SUMPRODUCT((Daily!$A$3:$A$302>=$C$4)*(Daily!$A$3:$A$302<=$C$5)*(Daily!$I$3:$I$302="")) | E27: A day priced at nothing earns nothing. Should never be anything but 0.
B28: 0 means the formulas are intact. It does NOT mean the numbers are right — a lead count typed wrong, or a lead logged in the wrong lane, passes all four silently.
B31: MONEY ALREADY TRANSFERRED | E31: Log every payment here, or the balance below will keep asking for money that has already moved.
B32: Date | C32: Paid by | D32: Amount | E32: Note
B59: Paid by Olivia to Bob | C59: =SUMIFS($D$33:$D$57,$C$33:$C$57,"Olivia",$B$33:$B$57,">="&$C$4,$B$33:$B$57,"<="&$C$5)
B60: Paid by Bob to Olivia | C60: =SUMIFS($D$33:$D$57,$C$33:$C$57,"Bob",$B$33:$B$57,">="&$C$4,$B$33:$B$57,"<="&$C$5)
B62: STILL OUTSTANDING | C62: =C21-C59+C60
B64: =IF(ROUND(C62,2)>0,"OLIVIA PAYS BOB "&TEXT(C62,"#,##0.00"),IF(ROUND(C62,2)<0,"BOB PAYS OLIVIA "&TEXT(-C62,"#,##0.00"),"NOTHING OWED — SETTLED"))

Sheet Example
A1: Example — three worked days, numbers typed in so you can check the maths
A2: Date | B2: Leads Bob's own -> Olivia | C2: Leads S -> Olivia | D2: Leads GS -> Olivia | E2: Leads Bob's own -> GLU | F2: Leads S -> GLU | G2: Leads GS -> GLU | H2: Total leads | I2: Price Bob -> Olivia per lead | J2: Price GS -> GLU per lead | K2: Panel fee per lead | L2: OLIVIA OWES BOB | M2: BOB OWES OLIVIA | N2: Other cost amount | O2: Other cost paid by | P2: Settle it? YES / NO | Q2: Other cost adjustment | R2: Who pays whom | S2: NET (+ Olivia pays Bob) (- Bob pays Olivia)
A3: 46244 | B3: 40 | C3: 0 | D3: 25 | E3: 10 | F3: 0 | G3: 12 | H3: =IF($A3="","",SUM($B3:$G3)) | I3: 8 | J3: 6 | K3: 0 | L3: =IF($A3="","",($B3+$C3)*$I3) | M3: =IF($A3="","",$G3*$J3+($E3+$F3+$G3)*$K3) | Q3: =IF($A3="","",IF($P3="YES",IF($O3="Bob",$N3,-$N3),0)) | R3: =IF($A3="","",IF(ROUND($S3,2)>0,"Olivia pays Bob "&TEXT($S3,"#,##0.00"),IF(ROUND($S3,2)<0,"Bob pays Olivia "&TEXT(-$S3,"#,##0.00"),"Nothing owed"))) | S3: =IF($A3="","",$L3-$M3+$Q3)
A4: 46245 | B4: 0 | C4: 35 | D4: 18 | E4: 0 | F4: 8 | G4: 20 | H4: =IF($A4="","",SUM($B4:$G4)) | I4: 8 | J4: 6 | K4: 0 | L4: =IF($A4="","",($B4+$C4)*$I4) | M4: =IF($A4="","",$G4*$J4+($E4+$F4+$G4)*$K4) | N4: 30 | O4: Bob | P4: YES | Q4: =IF($A4="","",IF($P4="YES",IF($O4="Bob",$N4,-$N4),0)) | R4: =IF($A4="","",IF(ROUND($S4,2)>0,"Olivia pays Bob "&TEXT($S4,"#,##0.00"),IF(ROUND($S4,2)<0,"Bob pays Olivia "&TEXT(-$S4,"#,##0.00"),"Nothing owed"))) | S4: =IF($A4="","",$L4-$M4+$Q4)
A5: 46246 | B5: 5 | C5: 0 | D5: 30 | E5: 2 | F5: 0 | G5: 45 | H5: =IF($A5="","",SUM($B5:$G5)) | I5: 8 | J5: 6 | K5: 0 | L5: =IF($A5="","",($B5+$C5)*$I5) | M5: =IF($A5="","",$G5*$J5+($E5+$F5+$G5)*$K5) | N5: 50 | O5: Olivia | P5: YES | Q5: =IF($A5="","",IF($P5="YES",IF($O5="Bob",$N5,-$N5),0)) | R5: =IF($A5="","",IF(ROUND($S5,2)>0,"Olivia pays Bob "&TEXT($S5,"#,##0.00"),IF(ROUND($S5,2)<0,"Bob pays Olivia "&TEXT(-$S5,"#,##0.00"),"Nothing owed"))) | S5: =IF($A5="","",$L5-$M5+$Q5)
